brutal_ng-0.3.11.dist-info/DESCRIPTION.rst
brutal_ng-0.3.11.dist-info/WHEEL
brutal_ng-0.3.11.dist-info/METADATA
brutal_ng-0.3.11.dist-info/RECORD
brutal_ng-0.3.11.dist-info/metadata.json
brutal_ng-0.3.11.dist-info/top_level.txt
brutal_ng-0.3.11.data/scripts/brutal-overlord.py
brutal/run.py
brutal/__init__.py
brutal/conf/global_config.py
brutal/conf/__init__.py
brutal/bin/brutal-overlord.py
brutal/spawn/spawn_template/hive.py
brutal/spawn/spawn_template/spawn_name/__init__.py
brutal/spawn/spawn_template/spawn_name/config.py
brutal/spawn/spawn_template/spawn_name/plugins/example.py
brutal/spawn/spawn_template/spawn_name/plugins/__init__.py
brutal/spawn/spawn_template/data/.gitignore
brutal/core/models.py
brutal/core/bot.py
brutal/core/management.py
brutal/core/plugin.py
brutal/core/connections.py
brutal/core/utils.py
brutal/core/__init__.py
brutal/core/constants.py
brutal/plugins/basic.py
brutal/plugins/__init__.py
brutal/protocols/xmpp.py
brutal/protocols/testconsole.py
brutal/protocols/core.py
brutal/protocols/irc.py
brutal/protocols/__init__.py
