Metadata-Version: 2.0
Name: brutal-ng
Version: 0.3.11
Summary: The new generation of brutal, a multi-network asynchronouschat bot framework using twisted
Home-page: https://github.com/xlcteam/brutal-ng
Author: XLC Team
Author-email: contact@mail.xlc-team.info
License: Copyright 2013 Corey Bertram and contributors.
Requires-Dist: Twisted (>=12.1.0)
Requires-Dist: wokkel (==0.7.1)
Requires-Dist: pyOpenSSL (==0.13)
Requires-Dist: service-identity (==14.0.0)
